context_explorer/__init__.py
context_explorer/cluster_cells.py
context_explorer/colony_overlays.py
context_explorer/data_processing.py
context_explorer/intensity_distributions.py
context_explorer/main.py
context_explorer/plot_colonies.py
context_explorer/visual_clustering.py
context_explorer/gui/__init__.py
context_explorer/gui/context_explorer_design.py
context_explorer/gui/mplwidget.py
context_explorer/gui/visual_clustering_gui.py
context_explorer-1.4.1.dist-info/METADATA
context_explorer-1.4.1.dist-info/RECORD
context_explorer-1.4.1.dist-info/WHEEL
context_explorer-1.4.1.dist-info/entry_points.txt
context_explorer-1.4.1.dist-info/top_level.txt
ctexplorer/__init__.py
ctexplorer/_version.py
ctexplorer/cluster_cells.py
ctexplorer/colony_overlays.py
ctexplorer/data_processing.py
ctexplorer/default_settings.py
ctexplorer/intensity_distributions.py
ctexplorer/log_test.py
ctexplorer/main.py
ctexplorer/plot_colonies.py
ctexplorer/visual_clustering.py
ctexplorer/gui/__init__.py
ctexplorer/gui/context_explorer_design.py
ctexplorer/gui/mplwidget.py
ctexplorer/gui/visual_clustering_gui.py
ctexplorer/icons/ce-icon-keep-white.ico
ctexplorer/icons/ce-icon-keep-white.png
ctexplorer/sample-data/ce-sample.csv
ctexplorer/tests/__init__.py
ctexplorer/tests/conftest.py
ctexplorer/tests/test_dataprocessing.py
