Metadata-Version: 2.1
Name: context-explorer
Version: 1.4.1
Summary: Context aware analysis of cell fate acquisitions
Home-page: https://gitlab.com/stemcellbioengineering/context-explorer
Author: Joel Ostblom
Author-email: joel.ostblom@gmail.com
License: BSD-3
Platform: UNKNOWN
Requires-Python: >=3.6
Requires-Dist: matplotlib
Requires-Dist: joblib
Requires-Dist: scikit-learn
Requires-Dist: joblib
Requires-Dist: numpy
Requires-Dist: pandas
Requires-Dist: shapely
Requires-Dist: matplotlib
Requires-Dist: natsort
Requires-Dist: seaborn
Requires-Dist: scipy
Requires-Dist: pyqt5
Requires-Dist: scikit-image
